college-football/__init__.py
college-football/college_football.py
college_football/__init__.py
college_football/college_football.py
college_football/player_module.py
college_football-0.0.5.dist-info/LICENSE
college_football-0.0.5.dist-info/METADATA
college_football-0.0.5.dist-info/WHEEL
college_football-0.0.5.dist-info/top_level.txt
college_football-0.0.5.dist-info/RECORD
