Metadata-Version: 2.1
Name: college-football
Version: 0.0.5
Summary: A college football analysis package
Home-page: https://github.com/zsurma/college-football
Author: Zoe Surma
Author-email: zdawg1022@gmail.com
License: UNKNOWN
Project-URL: Bug Tracker, https://github.com/zsurma/college-football/issues
Platform: UNKNOWN
Classifier: Programming Language :: Python :: 3
Classifier: License :: OSI Approved :: MIT License
Classifier: Operating System :: OS Independent
Requires-Python: >=3.8
